TableauDesktopPy/TableauDesktopPy.py
TableauDesktopPy/__init__.py
TableauDesktopPy/assets/README-twb.txt
TableauDesktopPy-1.1.1.dist-info/LICENSE
TableauDesktopPy-1.1.1.dist-info/METADATA
TableauDesktopPy-1.1.1.dist-info/WHEEL
TableauDesktopPy-1.1.1.dist-info/top_level.txt
TableauDesktopPy-1.1.1.dist-info/RECORD
