Metadata-Version: 2.1
Name: TableauDesktopPy
Version: 1.1.1
Summary: Tools for extracting metadata from Tableau Desktop workbook files.
Home-page: https://github.com/bpewyllie/tableaudesktoppy
Author: Brady Wyllie
Author-email: bpewyllie@gmail.com
License: UNKNOWN
Platform: UNKNOWN
Classifier: Programming Language :: Python :: 3
Classifier: License :: OSI Approved :: MIT License
Classifier: Operating System :: OS Independent
Requires-Python: >=3.6
